sgs/__init__.py
sgs/api.py
sgs/calculations.py
sgs/config.py
sgs/data/vox1_data.json
speech_gender_statistics-1.0.9.dist-info/METADATA
speech_gender_statistics-1.0.9.dist-info/WHEEL
speech_gender_statistics-1.0.9.dist-info/top_level.txt
speech_gender_statistics-1.0.9.dist-info/RECORD
