Metadata-Version: 2.1
Name: speech-gender-statistics
Version: 1.0.9
Summary: Using statistical methods to determine speech femininity/masculinity based on phonetic features
Home-page: https://github.com/hykilpikonna/SpeechGenderAnalysis
Author: Azalea Gui
Author-email: hykilpikonna@gmail.com
License: MIT
Platform: UNKNOWN
Requires-Python: >=3.8
Requires-Dist: praat-parselmouth
Requires-Dist: numpy
Requires-Dist: scipy
